{"cameraMode":{"drawMode":0,"name":"Shaded","section":"Shading Mode"},"sceneLighting":true,"audioPlay":false,"sceneViewState":{"m_AlwaysRefresh":false,"showFog":true,"showSkybox":true,"showFlares":true,"showImageEffects":true,"showParticleSystems":true,"showVisualEffectGraphs":true,"m_FxEnabled":true},"in2DMode":false,"pivot":{"x":38.2400016784668,"y":16.91359519958496,"z":-3.2062339782714845},"rotation":{"x":0.053267285227775577,"y":0.8736517429351807,"z":-0.09819991141557694,"w":0.47447821497917178},"size":36.625083923339847,"orthographic":false}